snakemake_storage_plugin_azure/__init__.py
snakemake_storage_plugin_azure/utils.py
snakemake_storage_plugin_azure-0.4.4.dist-info/LICENSE
snakemake_storage_plugin_azure-0.4.4.dist-info/METADATA
snakemake_storage_plugin_azure-0.4.4.dist-info/WHEEL
snakemake_storage_plugin_azure-0.4.4.dist-info/RECORD
