Metadata-Version: 2.3
Name: snakemake-storage-plugin-azure
Version: 0.4.4
Summary: A Snakemake storage plugin to read and write from Azure Blob Storage
License: MIT
Keywords: snakemake,plugin,storage,azure
Author: Jake VanCampen
Author-email: jake.vancampen7@gmail.com
Requires-Python: >=3.11,<4.0
Classifier: License :: OSI Approved :: MIT License
Classifier: Programming Language :: Python :: 3
Classifier: Programming Language :: Python :: 3.11
Classifier: Programming Language :: Python :: 3.12
Classifier: Programming Language :: Python :: 3.13
Requires-Dist: azure-core (>=1.30.2,<2.0.0)
Requires-Dist: azure-identity (>=1.17.1,<2.0.0)
Requires-Dist: azure-storage-blob (>=12.20.0,<13.0.0)
Requires-Dist: snakemake-interface-common (>=1.17.2,<2.0.0)
Requires-Dist: snakemake-interface-storage-plugins (>=4.1.0,<5.0.0)
Project-URL: Documentation, https://snakemake.github.io/snakemake-plugin-catalog/plugins/storage/azure.html
Project-URL: Repository, https://github.com/snakemake/snakemake-storage-plugin-azure
